drep/__init__.py
drep/cli.py
drep/cli_validators.py
drep/config.py
drep/constants.py
drep/server.py
drep/adapters/__init__.py
drep/adapters/base.py
drep/adapters/gitea.py
drep/adapters/github.py
drep/adapters/gitlab.py
drep/code_quality/__init__.py
drep/code_quality/analyzer.py
drep/core/__init__.py
drep/core/code_analyzer.py
drep/core/issue_manager.py
drep/core/llm_agent.py
drep/core/logging_config.py
drep/core/performance.py
drep/core/scanner.py
drep/db/__init__.py
drep/db/models.py
drep/db/repository.py
drep/docstring/__init__.py
drep/docstring/ast_utils.py
drep/docstring/generator.py
drep/documentation/__init__.py
drep/documentation/analyzer.py
drep/documentation/comment_gen.py
drep/documentation/llm_review.py
drep/llm/__init__.py
drep/llm/cache.py
drep/llm/circuit_breaker.py
drep/llm/client.py
drep/llm/metrics.py
drep/llm/providers/__init__.py
drep/llm/providers/bedrock_client.py
drep/models/__init__.py
drep/models/config.py
drep/models/docstring_findings.py
drep/models/findings.py
drep/models/llm_findings.py
drep/models/pr_review_findings.py
drep/models/webhook.py
drep/models/wizard.py
drep/pr_review/__init__.py
drep/pr_review/analyzer.py
drep/pr_review/diff_parser.py
drep/security/__init__.py
drep/security/detector.py
drep_ai-1.1.0.dist-info/METADATA
drep_ai-1.1.0.dist-info/WHEEL
drep_ai-1.1.0.dist-info/entry_points.txt
drep_ai-1.1.0.dist-info/licenses/LICENSE
drep_ai-1.1.0.dist-info/RECORD
