Metadata-Version: 2.4
Name: drep-ai
Version: 1.1.0
Summary: AI-powered code review and documentation quality tool for Gitea, GitHub, and GitLab
Project-URL: Homepage, https://github.com/slb350/drep
Project-URL: Repository, https://github.com/slb350/drep
Project-URL: Documentation, https://github.com/slb350/drep/tree/main/docs
Project-URL: Issues, https://github.com/slb350/drep/issues
Project-URL: Changelog, https://github.com/slb350/drep/blob/main/CHANGELOG.md
Author: drep Contributors
License: MIT
License-File: LICENSE
Keywords: automation,code-review,documentation,gitea,github,gitlab,linting,llm
Classifier: Development Status :: 5 - Production/Stable
Classifier: Intended Audience :: Developers
Classifier: License :: OSI Approved :: MIT License
Classifier: Programming Language :: Python :: 3
Classifier: Programming Language :: Python :: 3.10
Classifier: Programming Language :: Python :: 3.11
Classifier: Topic :: Software Development :: Documentation
Classifier: Topic :: Software Development :: Libraries :: Python Modules
Classifier: Topic :: Software Development :: Quality Assurance
Requires-Python: >=3.10
Requires-Dist: boto3>=1.34.0
Requires-Dist: click>=8.1.0
Requires-Dist: fastapi>=0.104.0
Requires-Dist: gitpython>=3.1.0
Requires-Dist: httpx>=0.25.0
Requires-Dist: open-agent-sdk>=0.1.0
Requires-Dist: pydantic>=2.5.0
Requires-Dist: pyyaml>=6.0
Requires-Dist: sqlalchemy>=2.0.0
Requires-Dist: uvicorn[standard]>=0.24.0
Provides-Extra: dev
Requires-Dist: black>=23.0; extra == 'dev'
Requires-Dist: build>=1.0.0; extra == 'dev'
Requires-Dist: mypy>=1.8.0; extra == 'dev'
Requires-Dist: pytest-asyncio>=0.21; extra == 'dev'
Requires-Dist: pytest-cov>=4.0; extra == 'dev'
Requires-Dist: pytest>=7.0; extra == 'dev'
Requires-Dist: respx>=0.20.0; extra == 'dev'
Requires-Dist: ruff>=0.5.0; extra == 'dev'
Requires-Dist: twine>=4.0.0; extra == 'dev'
Requires-Dist: types-pyyaml>=6.0.12; extra == 'dev'
